toonifier/__init__.py
toonifier/encoder.py
toonifier/exceptions.py
toonifier/parser.py
toonifier-0.1.1.dist-info/licenses/LICENSE
toonifier-0.1.1.dist-info/METADATA
toonifier-0.1.1.dist-info/WHEEL
toonifier-0.1.1.dist-info/top_level.txt
toonifier-0.1.1.dist-info/RECORD
