Metadata-Version: 2.4
Name: toonifier
Version: 0.1.1
Summary: A Python library for parsing and encoding Toon format files
Home-page: https://github.com/yourusername/pytoon
Author: Krishna Mishra
Author-email: Krishna Mishra <krishnamishra.dev@gmail.com>
Keywords: toon,parser,encoder
Classifier: Programming Language :: Python :: 3
Classifier: License :: OSI Approved :: MIT License
Requires-Python: >=3.10
License-File: LICENSE
Dynamic: license-file
